{
 "options": [
  {
   "n": 1,
   "text": "Коли є можливість, послати двох чоловік уздовж колій в обидва боки від переїзду не менш як на 1000 м (якщо одного, то в бік імовірної появи поїзда, а на одноколійних переїздах - у бік гіршої видимості залізничної колії), пояснивши їм правила подавання сигналу зупинки машиністу поїзда (локомотива, дрезини), що наближається."
  },
  {
   "n": 2,
   "text": "Залишатися біля транспортного засобу і, подаючи сигнали загальної тривоги, вживати всіх заходів для звільнення переїзду."
  },
  {
   "n": 3,
   "text": "У разі появи поїзда бігти йому назустріч, подаючи сигнал зупинки."
  },
  {
   "n": 4,
   "text": "Виконати все перераховане."
  }
 ],
 "answer": 4,
 "_note": "v12 verbatim exam-base: 1->4 (https://pomahach.com/question/3115-3286/yakih-zahodiv-povinen-vzhiti-vodiy-trans)"
}