{
 "chunk": 118,
 "section": "52",
 "isRuleSection": false,
 "rows": [
  {
   "label": "52",
   "qnum": 1,
   "text": "Що спільного у цих двох дорожніх знаків?",
   "options": [
    {
     "n": 1,
     "text": "Позначають заборону тільки для транзитного руху.",
     "correct": false
    },
    {
     "n": 2,
     "text": "Дозволяють рух спецтранспорту з помаранчевим маячком.",
     "correct": false
    },
    {
     "n": 3,
     "text": "Дозволяють рух маршрутних транспортних засобів.",
     "correct": true
    },
    {
     "n": 4,
     "text": "Після цих знаків починається зустрічний рух.",
     "correct": false
    }
   ],
   "correctText": "Дозволяють рух маршрутних транспортних засобів."
  },
  {
   "label": "52",
   "qnum": 2,
   "text": "Який із зображених дорожніх знаків встановлюється в кінці посадкового майданчика зупинки автобуса?",
   "options": [
    {
     "n": 1,
     "text": "Знак 1.",
     "correct": false
    },
    {
     "n": 2,
     "text": "Знак 2.",
     "correct": false
    },
    {
     "n": 3,
     "text": "Знак 3.",
     "correct": false
    },
    {
     "n": 4,
     "text": "Знак 4.",
     "correct": false
    },
    {
     "n": 5,
     "text": "Знак 5.",
     "correct": true
    }
   ],
   "correctText": "Знак 5."
  },
  {
   "label": "52",
   "qnum": 3,
   "text": "З якою максимальною швидкістю дозволено рух синього автобуса?",
   "options": [
    {
     "n": 1,
     "text": "70 км/год.",
     "correct": false
    },
    {
     "n": 2,
     "text": "80 км/год.",
     "correct": false
    },
    {
     "n": 3,
     "text": "90 км/год.",
     "correct": true
    },
    {
     "n": 4,
     "text": "100 км/год.",
     "correct": false
    },
    {
     "n": 5,
     "text": "110 км/год.",
     "correct": false
    }
   ],
   "correctText": "90 км/год."
  },
  {
   "label": "52",
   "qnum": 4,
   "text": "З якою максимальною швидкістю дозволено рух червоному автобусу на автомагістралі?",
   "options": [
    {
     "n": 1,
     "text": "70 км/год.",
     "correct": false
    },
    {
     "n": 2,
     "text": "80 км/год.",
     "correct": false
    },
    {
     "n": 3,
     "text": "90 км/год.",
     "correct": true
    },
    {
     "n": 4,
     "text": "100 км/год.",
     "correct": false
    },
    {
     "n": 5,
     "text": "130 км/год.",
     "correct": false
    }
   ],
   "correctText": "90 км/год."
  },
  {
   "label": "52",
   "qnum": 5,
   "text": "З якою максимальною швидкістю дозволено рух автобусів (за винятком мікроавтобусів) на дорогах, позначених знаком «Дорога для автомобілів»?",
   "options": [
    {
     "n": 1,
     "text": "80 км/год.",
     "correct": false
    },
    {
     "n": 2,
     "text": "90 км/год.",
     "correct": true
    },
    {
     "n": 3,
     "text": "100 км/год.",
     "correct": false
    },
    {
     "n": 4,
     "text": "110 км/год.",
     "correct": false
    },
    {
     "n": 5,
     "text": "130 км/год.",
     "correct": false
    }
   ],
   "correctText": "90 км/год."
  },
  {
   "label": "52",
   "qnum": 6,
   "text": "Яка максимальна швидкість встановлена для руху мікроавтобусів на автомагістралі?",
   "options": [
    {
     "n": 1,
     "text": "80 км/год.",
     "correct": false
    },
    {
     "n": 2,
     "text": "90 км/год.",
     "correct": false
    },
    {
     "n": 3,
     "text": "110 км/год.",
     "correct": false
    },
    {
     "n": 4,
     "text": "130 км/год.",
     "correct": true
    }
   ],
   "correctText": "130 км/год."
  },
  {
   "label": "52",
   "qnum": 7,
   "text": "З якою максимальною швидкістю допускається рух мікроавтобусів на дорогах з окремими проїзними частинами?",
   "options": [
    {
     "n": 1,
     "text": "80 км/год.",
     "correct": false
    },
    {
     "n": 2,
     "text": "90 км/год.",
     "correct": false
    },
    {
     "n": 3,
     "text": "110 км/год.",
     "correct": true
    },
    {
     "n": 4,
     "text": "130 км/год.",
     "correct": false
    }
   ],
   "correctText": "110 км/год."
  },
  {
   "label": "52",
   "qnum": 9,
   "text": "Хто з водіїв зупинився з порушенням Правил дорожнього руху на дорозі в населеному пункті, якщо відомо, що водії трактора і вантажного автомобіля з дозволеною максимальною масою понад 3,5 т зупинилися без необхідності завантаження чи розвантаження, а водій автобуса - без необхідності посадки або висадки пасажирів?",
   "options": [
    {
     "n": 1,
     "text": "Водії вантажного автомобіля, трактора та автобуса.",
     "correct": false
    },
    {
     "n": 2,
     "text": "Водії вантажного автомобіля і трактора.",
     "correct": true
    },
    {
     "n": 3,
     "text": "Водії всіх транспортних засобів.",
     "correct": false
    },
    {
     "n": 4,
     "text": "Ніхто не порушує.",
     "correct": false
    }
   ],
   "correctText": "Водії вантажного автомобіля і трактора."
  },
  {
   "label": "52",
   "qnum": 10,
   "text": "Чи дозволено поворот праворуч водієві автобуса, що рухається за встановленим маршрутом, у зображеній ситуації?",
   "options": [
    {
     "n": 1,
     "text": "Дозволено.",
     "correct": true
    },
    {
     "n": 2,
     "text": "Заборонено.",
     "correct": false
    }
   ],
   "correctText": "Дозволено."
  },
  {
   "label": "52",
   "qnum": 11,
   "text": "З якою максимальною швидкістю допускається рух мікроавтобусів на дорогах для автомобілів?",
   "options": [
    {
     "n": 1,
     "text": "80 км/год.",
     "correct": false
    },
    {
     "n": 2,
     "text": "90 км/год.",
     "correct": false
    },
    {
     "n": 3,
     "text": "110 км/год.",
     "correct": true
    },
    {
     "n": 4,
     "text": "130 км/год.",
     "correct": false
    }
   ],
   "correctText": "110 км/год."
  },
  {
   "label": "52",
   "qnum": 12,
   "text": "З    якою     максимальною швидкістю дозволено рух білому мікроавтобусу, що перевозить організовані групи дітей, на цій дорозі?",
   "options": [
    {
     "n": 1,
     "text": "130 км/год.",
     "correct": false
    },
    {
     "n": 2,
     "text": "110 км/год.",
     "correct": false
    },
    {
     "n": 3,
     "text": "90 км/год.",
     "correct": false
    },
    {
     "n": 4,
     "text": "80 км/год.",
     "correct": true
    }
   ],
   "correctText": "80 км/год."
  },
  {
   "label": "52",
   "qnum": 13,
   "text": "З якою максимальною швидкістю дозволено рух жовтого автобуса, що перевозить організовану групу дітей, на цій ділянці дороги за межами населених пунктів?",
   "options": [
    {
     "n": 1,
     "text": "110 км/год.",
     "correct": false
    },
    {
     "n": 2,
     "text": "90 км/год.",
     "correct": false
    },
    {
     "n": 3,
     "text": "80 км/год.",
     "correct": true
    }
   ],
   "correctText": "80 км/год."
  },
  {
   "label": "52",
   "qnum": 14,
   "text": "Чи дозволено поворот ліворуч водієві автобуса, що рухається за встановленим маршрутом, у зображеній ситуації?",
   "options": [
    {
     "n": 1,
     "text": "Дозволено.",
     "correct": true
    },
    {
     "n": 2,
     "text": "Заборонено.",
     "correct": false
    }
   ],
   "correctText": "Дозволено."
  },
  {
   "label": "52",
   "qnum": 15,
   "text": "Чи дозволено автобусу, який рухається        за     встановленим маршрутом, повернути праворуч на зображеному перехресті?",
   "options": [
    {
     "n": 1,
     "text": "Заборонено.",
     "correct": false
    },
    {
     "n": 2,
     "text": "Дозволено.",
     "correct": true
    }
   ],
   "correctText": "Дозволено."
  },
  {
   "label": "52",
   "qnum": 16,
   "text": "Чи дозволено водієві автобуса, що рухається за встановленим маршрутом, повернути ліворуч у зображеній ситуації?",
   "options": [
    {
     "n": 1,
     "text": "Дозволено.",
     "correct": true
    },
    {
     "n": 2,
     "text": "Заборонено.",
     "correct": false
    }
   ],
   "correctText": "Дозволено."
  }
 ]
}