{
  "key": "15:75",
  "short": "Зупинка дозволяється не ближче ніж за 10 м до пішохідного переходу з обох боків, бо ПДР забороняють зупинку та стоянку на самому переході й ближче 10 м від нього.",
  "detailed": "Згідно з п. 15.9 ПДР зупинка і стоянка заборонені на пішохідних переходах та ближче 10 м від них з обох боків. Ця норма потрібна, щоб транспортні засоби, які стоять, не обмежували оглядовість пішоходам і водіям перед переходом. Тому правильним є варіант про відстань не менше 10 м з обох боків від переходу. Відповіді з 20 і 30 м встановлюють надмірну відстань, а варіант «10 м до переходу» не враховує вимогу «з обох боків».",
  "legalRef": "п. 15.9",
  "image_dependent": false,
  "answer_ok": true,
  "conflict_note": "",
  "suggested_answer": null
}
