{"key":"19:19","short":"При в'їзді в тунель водій механічного транспортного засобу зобов'язаний увімкнути ближнє або дальнє світло фар, тому правильна відповідь - третя.","detailed":"Згідно з ПДР, у тунелях незалежно від ступеня їх освітлення на механічному транспортному засобі мають бути ввімкнені ближнє або дальнє світло фар - так само, як у темну пору доби та в умовах недостатньої видимості. Габаритні ліхтарі лише позначають габарити ТЗ і не забезпечують потрібного освітлення дороги, а протитуманні фари застосовуються в умовах туману, дощу чи снігопаду, а не як обов'язкове світло в тунелі. Тому навіть в освітленому тунелі обов'язковим є саме ближнє або дальнє світло фар.","legalRef":"п. 19.1","image_dependent":false,"answer_ok":true,"conflict_note":"","suggested_answer":null}
