{
  "key": "1:76",
  "short": "Наведене формулювання — це визначення терміна «Дорожня обстановка», тому правильна відповідь третя.",
  "detailed": "Згідно з розділом 1.10 ПДР, дорожня обстановка — це сукупність факторів, що характеризуються дорожніми умовами, наявністю перешкод на ділянці дороги, інтенсивністю та рівнем організації дорожнього руху (стан розмітки, знаків, дорожнього обладнання, світлофорів), які водій повинен ураховувати під час вибору швидкості, смуги руху та прийомів керування. «Дорожні умови» — лише частина цих факторів (стан покриття, видимість, освітлення тощо), а «дорожні роботи» — окреме поняття про ремонт чи будівництво дороги. Текст питання дослівно збігається з визначенням саме дорожньої обстановки.",
  "legalRef": "п. 1.10",
  "image_dependent": false,
  "answer_ok": true,
  "conflict_note": "",
  "suggested_answer": null
}
