{
  "key": "33:180",
  "short": "Попереджувальний знак 1.24 «Світлофорне регулювання» інформує про наближення до перехрестя, пішохідного переходу або ділянки дороги, рух на яких регулюється світлофором, тому правильними є всі три варіанти (відповідь 5).",
  "detailed": "Знак 1.24 «Світлофорне регулювання» належить до попереджувальних знаків і встановлюється для завчасного інформування водія про те, що попереду рух регулюється світлофором. Він застосовується незалежно від того, де саме розташований світлофор — на перехресті, перед пішохідним переходом чи на іншій ділянці дороги. Оскільки знак охоплює всі ці випадки, твердження 1, 2 і 3 є правильними одночасно, що відповідає варіанту «Відповіді 1, 2 і 3».",
  "legalRef": "знак 1.24 (Додаток 1 до ПДР)",
  "image_dependent": true,
  "answer_ok": true,
  "conflict_note": "",
  "suggested_answer": null
}
