{
  "key": "33:126",
  "short": "Спільна ознака цих двох знаків у тому, що жоден із них не забороняє поворот праворуч — саме тому правильний варіант про те, що вони не забороняють поворот направо.",
  "detailed": "Питання зображувальне: треба порівняти два конкретні дорожні знаки на малюнку та знайти їх спільну рису. Серед запропонованих варіантів лише той, що обидва знаки не забороняють поворот направо, описує властивість, притаманну обом знакам одночасно. Інші варіанти (встановлення лише на Т-подібних перехрестях, безумовний дозвіл розвороту, рух прямо для маршрутних ТЗ) є надто вузькими або стосуються не обох знаків, тому не можуть бути спільною ознакою.",
  "legalRef": "",
  "image_dependent": true,
  "answer_ok": true,
  "conflict_note": "",
  "suggested_answer": null
}
