{"key":"33:232","short":"Зазначений варіант описує попереджувальний знак 1.34 «Тунель», який попереджає водія про наближення до споруди без штучного освітлення, з обмеженою оглядовістю в'їзного порталу або зі звуженою на під'їзді проїзною частиною.","detailed":"Питання стосується конкретного попереджувального знака, зображеного на малюнку. Якщо це знак 1.34 «Тунель», він установлюється перед в'їздом у тунель (споруду), що не має штучного освітлення, оглядовість в'їзного порталу якої обмежена або до якого звужується проїзна частина, аби водій завчасно знизив швидкість, увімкнув ближнє світло фар і був готовий до руху в умовах обмеженої видимості. Інші варіанти описують інші попереджувальні знаки — наближення до мосту, шляхопроводу чи залізничного переїзду, що мають власні зображення та значення. Точна відповідність визначається саме зображенням знака.","legalRef":"знак 1.34 «Тунель» (Розділ 33 ПДР, попереджувальні знаки)","image_dependent":true,"answer_ok":true,"conflict_note":"","suggested_answer":null}
