{
  "key": "43:30",
  "short": "Правильна відповідь — варіант 3: треба зменшити швидкість (за потреби зупинитися) і продовжувати рух лише переконавшись, що на переході немає пішоходів, яким можна створити перешкоду чи небезпеку.",
  "detailed": "Якщо транспортний засіб, що рухається попереду в попутному напрямку, сповільнює рух або зупиняється перед нерегульованим пішохідним переходом, це є ознакою того, що попереду можуть бути пішоходи, яких ваш огляд не охоплює. ПДР прямо забороняють у такій ситуації об'їжджати чи проїжджати перехід «з ходу»: водій зобов'язаний зменшити швидкість, у разі потреби зупинитися, і рушати далі тільки після того, як особисто переконається у відсутності пішоходів, для яких може бути створена перешкода або небезпека. Тому варіанти зі звуковим сигналом чи з простим «обережним проїздом» переходу є неправильними, бо не гарантують безпеки пішоходів.",
  "legalRef": "п. 18.2 (також п. 18.1)",
  "image_dependent": false,
  "answer_ok": true,
  "conflict_note": "",
  "suggested_answer": null
}
