{
  "key": "48:30",
  "short": "Правильна відповідь — варіант 4 («Відповіді 1, 2 і 3»): зображений заборонний знак поширюється одразу на всі перелічені категорії транспортних засобів — ті, що перевозять цистерни, небезпечні вантажі та речовини, які забруднюють воду.",
  "detailed": "Заборонні знаки вводять обмеження на рух окремих категорій транспортних засобів і діють від місця встановлення. Зображений знак належить до групи знаків, що забороняють рух транспортних засобів із небезпечними та спеціальними вантажами, тому охоплює і перевезення в цистернах, і небезпечні вантажі загалом, і речовини, які забруднюють воду. Через це жоден із варіантів 1–3 окремо не є повним, а правильною є узагальнювальна відповідь 4, яка об'єднує всі три категорії.",
  "legalRef": "Додаток 1 до ПДР (заборонні знаки)",
  "image_dependent": true,
  "answer_ok": true,
  "conflict_note": "",
  "suggested_answer": null
}
