{"key":"4:11","short":"Пішоходи мають дійти до розділювальної смуги (як до острівця безпеки) і чекати на ній, продовживши перехід лише тоді, коли це дозволить відповідний сигнал світлофора, — тому правильна відповідь 2.","detailed":"Згідно з ПДР пішохід, для якого під час переходу проїзної частини одного напрямку ввімкнувся заборонний сигнал, не повинен ні бігти вперед через зустрічний потік, ні повертатися назад. Розділювальна смуга в такій ситуації відіграє роль безпечного місця (на кшталт острівця безпеки чи лінії поділу зустрічних потоків): пішоход має завершити рух до неї та зупинитися. Продовжити перехід дозволено лише за дозвільним сигналом світлофора і після того, як він переконається в безпеці подальшого руху. Тому правильна відповідь 2; варіант 1 («завершити перехід на будь-якому сигналі») хибний, бо змусив би пішохода перетинати другу проїзну частину всупереч заборонному сигналу й створювати небезпеку.","legalRef":"п. 4.14","image_dependent":false,"answer_ok":true,"conflict_note":"","suggested_answer":null}
