{"key":"9:40","short":"Сигнал світловим покажчиком повороту слід припиняти негайно після того, як маневр повністю завершено, тому правильна відповідь — «Відразу після завершення маневру».","detailed":"Згідно з ПДР, сигнал повороту або перестроювання водій повинен подавати завчасно до початку маневру, щоб попередити інших учасників дорожнього руху про свої наміри, і не вимикати його під час самого маневру. Подавання сигналу світловим покажчиком повороту припиняється негайно після завершення маневру. Тому вимкнення сигналу перед початком маневру (варіант 1) чи під час його виконання (варіант 3) є помилковим — це може ввести в оману інших водіїв.","legalRef":"п. 9.3","image_dependent":false,"answer_ok":true,"conflict_note":"","suggested_answer":null}
