{
 "chunk": 20,
 "rows": [
  {
   "label": "35",
   "qnum": 15,
   "text": "При проїзді через тунель ви наближаєтеся до кінця затору. Як Вам вести себе?",
   "options": [
    {
     "n": 1,
     "text": "Розвернути транспортний засіб і залишити тунель."
    },
    {
     "n": 2,
     "text": "В кінці затору вимкнути двигун і залишити транспортний засіб."
    },
    {
     "n": 3,
     "text": "Включити аварійну світлову сигналізацію."
    },
    {
     "n": 4,
     "text": "Всі відповіді вірні."
    }
   ],
   "correctText": "Включити аварійну світлову сигналізацію.",
   "section": "35"
  },
  {
   "label": "35",
   "qnum": 16,
   "text": "Ви хочете обігнати велосипедистів. Що Ви повинні врахувати при оцінці бокового інтервалу?",
   "options": [
    {
     "n": 1,
     "text": "Бокова відстань в 1,0 м є завжди достатньою."
    },
    {
     "n": 2,
     "text": "Поведінка велосипедистів."
    },
    {
     "n": 3,
     "text": "Швидкість свого транспортного засобу."
    },
    {
     "n": 4,
     "text": "Відповіді 2 і 3."
    }
   ],
   "correctText": "Відповіді 2 і 3.",
   "section": "35"
  },
  {
   "label": "35",
   "qnum": 19,
   "text": "Як сприймається водієм швидкість його автомобіля у випадку тривалого руху рівнинною дорогою з великою швидкістю?",
   "options": [
    {
     "n": 1,
     "text": "Здається менше, ніж насправді."
    },
    {
     "n": 2,
     "text": "Здається більшою, ніж насправді."
    },
    {
     "n": 3,
     "text": "Сприйняття швидкості не змінюється."
    }
   ],
   "correctText": "Здається менше, ніж насправді.",
   "section": "35"
  },
  {
   "label": "35",
   "qnum": 20,
   "text": "Під час руху на якому автомобілі збільшення швидкості може сприяти усуненню занесення задньої осі?",
   "options": [
    {
     "n": 1,
     "text": "На передньопривідному."
    },
    {
     "n": 2,
     "text": "На задньопривідному."
    }
   ],
   "correctText": "На передньопривідному.",
   "section": "35"
  },
  {
   "label": "35",
   "qnum": 21,
   "text": "Що має зробити водій, щоб швидко відновити ефективність гальм після проїзду через водну перешкоду?",
   "options": [
    {
     "n": 1,
     "text": "Продовжити рух, трохи натягнувши важіль ручного гальма."
    },
    {
     "n": 2,
     "text": "Продовжити рух і просушити гальмівні колодки багаторазовими нетривалими натисканнями на педаль гальма."
    },
    {
     "n": 3,
     "text": "Продовжити рух із малою швидкістю без пригальмовування."
    }
   ],
   "correctText": "Продовжити рух і просушити гальмівні колодки багаторазовими нетривалими натисканнями на педаль гальма.",
   "section": "35"
  },
  {
   "label": "35",
   "qnum": 22,
   "text": "Під час гальмування двигуном на крутому спуску водій має вибирати передачу, виходячи з умов:",
   "options": [
    {
     "n": 1,
     "text": "Чим крутіше спуск, тим вище передача."
    },
    {
     "n": 2,
     "text": "Чим крутіше спуск, тим нижче передача."
    },
    {
     "n": 3,
     "text": "Вибір передачі не залежить від крутизни спуску."
    }
   ],
   "correctText": "Чим крутіше спуск, тим нижче передача.",
   "section": "35"
  },
  {
   "label": "35",
   "qnum": 23,
   "text": "Як має діяти водій у разі втрати зчеплення коліс з дорогою через утворення «водяного клина»?",
   "options": [
    {
     "n": 1,
     "text": "Збільшити швидкість."
    },
    {
     "n": 2,
     "text": "Знизити швидкість різким натисканням на педаль гальма."
    },
    {
     "n": 3,
     "text": "Знизити швидкість, застосовуючи гальмування двигуном."
    }
   ],
   "correctText": "Знизити швидкість, застосовуючи гальмування двигуном.",
   "section": "35"
  },
  {
   "label": "35",
   "qnum": 25,
   "text": "Під час руху в умовах туману відстань до предметів видається:",
   "options": [
    {
     "n": 1,
     "text": "Більшою, ніж насправді."
    },
    {
     "n": 2,
     "text": "Меншою, ніж насправді."
    },
    {
     "n": 3,
     "text": "Такою, що відповідає дійсності."
    }
   ],
   "correctText": "Більшою, ніж насправді.",
   "section": "35"
  },
  {
   "label": "35",
   "qnum": 26,
   "text": "Що мається на увазі під зупинним шляхом?",
   "options": [
    {
     "n": 1,
     "text": "Відстань, пройдена транспортним засобом з моменту виявлення водієм небезпеки до повної зупинки."
    },
    {
     "n": 2,
     "text": "Відстань, пройдена транспортним засобом з моменту початку спрацьовування гальмівного приводу до повної зупинки."
    },
    {
     "n": 3,
     "text": "Відстань, що відповідає гальмівному шляху, визначеному технічною характеристикою даного транспортного засобу."
    }
   ],
   "correctText": "Відстань, пройдена транспортним засобом з моменту виявлення водієм небезпеки до повної зупинки.",
   "section": "35"
  },
  {
   "label": "35",
   "qnum": 27,
   "text": "Якими критеріями мають керуватися водії, обираючи швидкість у відповідності до видимості за напрямком руху?",
   "options": [
    {
     "n": 1,
     "text": "Швидкість руху і видимість дороги між собою не пов‘язані."
    },
    {
     "n": 2,
     "text": "У населеному пункті, при виборі швидкості руху, на видимість можна не зважати."
    },
    {
     "n": 3,
     "text": "Чим гірша видимість, тим меншою має бути швидкість руху."
    }
   ],
   "correctText": "Чим гірша видимість, тим меншою має бути швидкість руху.",
   "section": "35"
  },
  {
   "label": "35",
   "qnum": 28,
   "text": "У якому випадку легковий автомобіль більш стійкий проти перекидання на повороті?",
   "options": [
    {
     "n": 1,
     "text": "Без вантажу і пасажирів."
    },
    {
     "n": 2,
     "text": "З пасажирами, але без вантажу."
    },
    {
     "n": 3,
     "text": "Без пасажирів, але з вантажем на верхньому багажнику."
    }
   ],
   "correctText": "Без вантажу і пасажирів.",
   "section": "35"
  },
  {
   "label": "35",
   "qnum": 30,
   "text": "У який момент слід поступово відпускати стоянкове гальмо, починаючи рух на підйомі?",
   "options": [
    {
     "n": 1,
     "text": "До початку руху."
    },
    {
     "n": 2,
     "text": "Після початку руху."
    },
    {
     "n": 3,
     "text": "Одночасно з початком руху."
    }
   ],
   "correctText": "Одночасно з початком руху.",
   "section": "35"
  },
  {
   "label": "35",
   "qnum": 31,
   "text": "Під час руху якою ділянкою дороги дія сильного бокового вітру найбільш небезпечна?",
   "options": [
    {
     "n": 1,
     "text": "Відкритою."
    },
    {
     "n": 2,
     "text": "Закритою деревами."
    },
    {
     "n": 3,
     "text": "Під час виїзду з закритої ділянки на відкриту."
    }
   ],
   "correctText": "Під час виїзду з закритої ділянки на відкриту.",
   "section": "35"
  },
  {
   "label": "35",
   "qnum": 33,
   "text": "Як змінюється поле зору водія зі збільшенням швидкості руху?",
   "options": [
    {
     "n": 1,
     "text": "Не змінюється."
    },
    {
     "n": 2,
     "text": "Розширюється."
    },
    {
     "n": 3,
     "text": "Звужується."
    }
   ],
   "correctText": "Звужується.",
   "section": "35"
  },
  {
   "label": "35",
   "qnum": 34,
   "text": "Який стиль водіння забезпечить найменшу витрату палива?",
   "options": [
    {
     "n": 1,
     "text": "Часте і різке прискорення при плавному уповільненні."
    },
    {
     "n": 2,
     "text": "Плавне прискорення при різкому уповільненні."
    },
    {
     "n": 3,
     "text": "Плавне прискорення при плавному уповільненні."
    }
   ],
   "correctText": "Плавне прискорення при плавному уповільненні.",
   "section": "35"
  },
  {
   "label": "35",
   "qnum": 35,
   "text": "Як змінюється довжина гальмівного шляху легкового автомобіля під час руху з причепом, не оснащеним гальмівною системою?",
   "options": [
    {
     "n": 1,
     "text": "Зменшується, оскільки причіп чинить додатковий опір руху."
    },
    {
     "n": 2,
     "text": "Збільшується."
    },
    {
     "n": 3,
     "text": "Не змінюється."
    }
   ],
   "correctText": "Збільшується.",
   "section": "35"
  },
  {
   "label": "35",
   "qnum": 36,
   "text": "Як слід вчинити водієві, якщо під час руху сухою дорогою з асфальтобетонним покриттям почав накрапати дощ?",
   "options": [
    {
     "n": 1,
     "text": "Зменшити швидкість і бути особливо обережним."
    },
    {
     "n": 2,
     "text": "Не змінюючи швидкості, продовжити рух."
    },
    {
     "n": 3,
     "text": "Збільшити швидкість і спробувати проїхати якомога більшу відстань, поки не почався сильний дощ."
    }
   ],
   "correctText": "Зменшити швидкість і бути особливо обережним.",
   "section": "35"
  },
  {
   "label": "35",
   "qnum": 37,
   "text": "Для припинення занесення, викликаного гальмуванням, водій у першу чергу має:",
   "options": [
    {
     "n": 1,
     "text": "Припинити розпочате гальмування."
    },
    {
     "n": 2,
     "text": "Вимкнути зчеплення."
    },
    {
     "n": 3,
     "text": "Продовжити гальмування, не змінюючи зусилля на педаль гальма."
    }
   ],
   "correctText": "Припинити розпочате гальмування.",
   "section": "35"
  },
  {
   "label": "35",
   "qnum": 38,
   "text": "У темну пору доби та в похмуру          погоду швидкість зустрічного автомобіля видається:",
   "options": [
    {
     "n": 1,
     "text": "Нижчою, ніж насправді."
    },
    {
     "n": 2,
     "text": "Вищою, ніж насправді."
    },
    {
     "n": 3,
     "text": "Сприйняття швидкості не змінюється."
    }
   ],
   "correctText": "Нижчою, ніж насправді.",
   "section": "35"
  },
  {
   "label": "35",
   "qnum": 42,
   "text": "Якщо виникла нагальна необхідність здійснити поїздку під час снігопаду, що рекомендовано мати з собою водієві?",
   "options": [
    {
     "n": 1,
     "text": "Лопату."
    },
    {
     "n": 2,
     "text": "Теплу ковдру."
    },
    {
     "n": 3,
     "text": "Щітку зі скребком."
    },
    {
     "n": 4,
     "text": "Повний бак пального."
    },
    {
     "n": 5,
     "text": "Все перераховане вище."
    }
   ],
   "correctText": "Все перераховане вище.",
   "section": "35"
  }
 ]
}